EmuPBk/__init__.py
EmuPBk/build.py
EmuPBk/models.py
EmuPBk/visualize.py
EmuPBk/MCMC/__init__.py
EmuPBk/MCMC/core.py
EmuPBk/MCMC/like.py
EmuPBk/MCMC/sampler.py
EmuPBk/MCMC/existing_models/bk.h5
EmuPBk/MCMC/existing_models/pk.h5
EmuPBk/tests/__init__.py
EmuPBk-6.5.4.dist-info/LICENSE.txt
EmuPBk-6.5.4.dist-info/METADATA
EmuPBk-6.5.4.dist-info/WHEEL
EmuPBk-6.5.4.dist-info/top_level.txt
EmuPBk-6.5.4.dist-info/RECORD
